{
 "SoundBanksInfo": {
  "Platform": "Windows",
  "BasePlatform": "Windows",
  "SchemaVersion": "12",
  "SoundbankVersion": "135",
  "RootPaths": {
   "ProjectRoot": "G:\\Unreal\\Djinniya\\Unreal\\DemoDay424\\Wwise_Prj\\DjinniyasLamp424\\",
   "SourceFilesRoot": "G:\\Unreal\\Djinniya\\Unreal\\DemoDay424\\Wwise_Prj\\DjinniyasLamp424\\.cache\\Windows\\",
   "SoundBanksRoot": "G:\\Unreal\\Djinniya\\Unreal\\DemoDay424\\Wwise_Prj\\DjinniyasLamp424\\GeneratedSoundBanks\\Windows\\",
   "ExternalSourcesInputFile": "",
   "ExternalSourcesOutputRoot": "G:\\Unreal\\Djinniya\\Unreal\\DemoDay424\\Wwise_Prj\\DjinniyasLamp424\\GeneratedSoundBanks\\Windows"
  },
  "SoundBanks": [
   {
    "Id": "1202187525",
    "GUID": "{5D725E50-346D-4F0A-B968-8F15F09F92CF}",
    "Language": "SFX",
    "ObjectPath": "\\SoundBanks\\Default Work Unit\\Master_SB",
    "ShortName": "Master_SB",
    "Path": "Master_SB.bnk"
   }
  ]
 }
}